tempocli/__init__.py
tempocli/__main__.py
tempocli/cli.py
tempocli/client.py
tempocli/funcs.py
tempocli/requests.py
tempocli/version.py
tempocli-0.2.4.dist-info/LICENSE
tempocli-0.2.4.dist-info/METADATA
tempocli-0.2.4.dist-info/WHEEL
tempocli-0.2.4.dist-info/entry_points.txt
tempocli-0.2.4.dist-info/top_level.txt
tempocli-0.2.4.dist-info/RECORD
